boolean_query_parser/__init__.py
boolean_query_parser/parser.py
boolean_query_parser-1.0.1.dist-info/licenses/LICENSE
tests/__init__.py
tests/test_parser.py
boolean_query_parser-1.0.1.dist-info/METADATA
boolean_query_parser-1.0.1.dist-info/WHEEL
boolean_query_parser-1.0.1.dist-info/top_level.txt
boolean_query_parser-1.0.1.dist-info/RECORD
