Metadata-Version: 2.4
Name: boolean_query_parser
Version: 1.0.1
Summary: A Python package for parsing and evaluating boolean text queries
Home-page: https://github.com/Piergiuseppe/boolean-query-parser
Author: Piergiuseppe D'Abbraccio
Author-email: piergiuseppedabbraccio@gmail.com
Project-URL: Bug Reports, https://github.com/Piergiuseppe/boolean-query-parser/issues
Project-URL: Source, https://github.com/Piergiuseppe/boolean-query-parser
Keywords: boolean,query,parser,text,search
Classifier: Programming Language :: Python :: 3
Classifier: Programming Language :: Python :: 3.13
Classifier: License :: OSI Approved :: MIT License
Classifier: Operating System :: OS Independent
Classifier: Development Status :: 3 - Alpha
Classifier: Intended Audience :: Developers
Classifier: Topic :: Text Processing :: General
Requires-Python: >=3.9
License-File: LICENSE
Requires-Dist: regex>=2021.8.3
Dynamic: author
Dynamic: author-email
Dynamic: classifier
Dynamic: description
Dynamic: description-content-type
Dynamic: home-page
Dynamic: keywords
Dynamic: license-file
Dynamic: project-url
Dynamic: requires-dist
Dynamic: requires-python
Dynamic: summary
